friday_sdk/__init__.py
friday_sdk/friday.py
friday_sdk-0.2.0.dist-info/METADATA
friday_sdk-0.2.0.dist-info/WHEEL
friday_sdk-0.2.0.dist-info/top_level.txt
friday_sdk-0.2.0.dist-info/RECORD
